{"births":{"totals":{"1680":"2","1710":"3","1740":"3","1760":"1","1770":"3","1780":"4","1790":"2","1800":"4","1810":"15","1820":"9","1830":"5","1840":"4","1850":"11","1860":"5","1870":"9","1880":"23","1890":"13","1560":0,"1570":0,"1580":0,"1590":0,"1600":0,"1610":0,"1620":0,"1630":0,"1640":0,"1650":0,"1660":0,"1670":0,"1690":0,"1700":0,"1720":0,"1730":0,"1750":0},"girls":{"1560":[],"1570":[],"1580":[],"1590":[],"1600":[],"1610":[],"1620":[],"1630":[],"1640":[],"1650":[],"1660":[],"1670":[],"1680":[{"forename":"ANN","count":"1"},{"forename":"MARGARET","count":"1"}],"1690":[],"1700":[],"1710":[{"forename":"GRIZELL","count":"1"},{"forename":"CATHARINE","count":"1"}],"1720":[],"1730":[],"1740":[{"forename":"ELIZABETH","count":"1"},{"forename":"ANNA","count":"1"}],"1750":[],"1760":[{"forename":"JEAN","count":"1"}],"1770":[{"forename":"ANNA","count":"1"},{"forename":"HELEN","count":"1"}],"1780":[{"forename":"ANN","count":"1"},{"forename":"CHRISTIAN","count":"1"}],"1790":[{"forename":"AGNES","count":"1"},{"forename":"ISABEL","count":"1"}],"1800":[{"forename":"MARY","count":"1"}],"1810":[{"forename":"CHRISTIAN","count":"1"},{"forename":"ANN","count":"1"},{"forename":"JEAN","count":"1"},{"forename":"JANE","count":"1"},{"forename":"MARY","count":"1"}],"1820":[{"forename":"MARY","count":"2"},{"forename":"JANET","count":"1"}],"1830":[{"forename":"-----","count":"1"},{"forename":"JANET MELLVILE","count":"1"},{"forename":"ANN","count":"1"}],"1840":[{"forename":"JANET","count":"1"},{"forename":"BETSY","count":"1"}],"1850":[{"forename":"JANE","count":"1"},{"forename":"JEAN BELL","count":"1"},{"forename":"JESSIE MELVILLE","count":"1"},{"forename":"JOHANNA","count":"1"}],"1860":[{"forename":"JANET","count":"1"},{"forename":"JANET MELVILLE","count":"1"},{"forename":"MARY YOOL","count":"1"}],"1870":[{"forename":"MAGDALENE SCOTT","count":"1"},{"forename":"MARY YOOL","count":"1"},{"forename":"AGNES KINGHORN","count":"1"},{"forename":"JANET REID","count":"1"},{"forename":"JESSIE JOHNSTON","count":"1"}],"1880":[{"forename":"MARGARET","count":"3"},{"forename":"AGNES REID","count":"1"},{"forename":"MAGGIE NISBET","count":"1"},{"forename":"MARGARET STEWAR","count":"1"},{"forename":"CATHERINE","count":"1"}],"1890":[{"forename":"ELIZABETH GEDDI","count":"1"},{"forename":"ANNIE JOHNSTONE","count":"1"},{"forename":"FLORA MACDONALD","count":"1"},{"forename":"ELIZABETH","count":"1"},{"forename":"JOAN MAGGIE STE","count":"1"}]},"boys":{"1560":[],"1570":[],"1580":[],"1590":[],"1600":[],"1610":[],"1620":[],"1630":[],"1640":[],"1650":[],"1660":[],"1670":[],"1680":[],"1690":[],"1700":[],"1710":[{"forename":"ROBERT","count":"1"}],"1720":[],"1730":[],"1740":[{"forename":"ROBERT","count":"1"}],"1750":[],"1760":[],"1770":[{"forename":"JOHN","count":"1"}],"1780":[{"forename":"JOHN","count":"1"},{"forename":"GEORGE","count":"1"}],"1790":[],"1800":[{"forename":"ROBERT","count":"2"},{"forename":"WILLIAM","count":"1"}],"1810":[{"forename":"JAMES","count":"3"},{"forename":"ALEXANDER","count":"2"},{"forename":"ROBERT","count":"2"},{"forename":"WILLIAM","count":"1"},{"forename":"DAVID","count":"1"}],"1820":[{"forename":"JAMES","count":"2"},{"forename":"JOHN","count":"1"},{"forename":"PETER","count":"1"},{"forename":"ALEXANDER","count":"1"},{"forename":"WILLIAM","count":"1"}],"1830":[{"forename":"ALEXANDER","count":"1"},{"forename":"DAVID","count":"1"}],"1840":[{"forename":"THOMAS YOOL","count":"1"},{"forename":"JAMES","count":"1"}],"1850":[{"forename":"WILLIAM YOOL","count":"1"},{"forename":"JAMES","count":"1"},{"forename":"JOHN","count":"1"},{"forename":"DAVID","count":"1"},{"forename":"PETER","count":"1"}],"1860":[{"forename":"ROBERT STEWART","count":"1"},{"forename":"JOHN","count":"1"}],"1870":[{"forename":"DAVID","count":"1"},{"forename":"JAMES","count":"1"},{"forename":"PETER MELVILLE","count":"1"},{"forename":"ROBERT WATT","count":"1"}],"1880":[{"forename":"ROBERT EDINGTON","count":"1"},{"forename":"DAVID DUNCAN","count":"1"},{"forename":"ANDREW EDINGTON","count":"1"},{"forename":"ROBERT","count":"1"},{"forename":"JOHN","count":"1"}],"1890":[{"forename":"ROBERT","count":"1"},{"forename":"DAVID STEWART","count":"1"},{"forename":"ALEXANDER CAMER","count":"1"},{"forename":"JAMES ROBERT","count":"1"},{"forename":"JAMES","count":"1"}]},"topParishes":{"1560":[],"1570":[],"1580":[],"1590":[],"1600":[],"1610":[],"1620":[],"1630":[],"1640":[],"1650":[],"1660":[],"1670":[],"1680":[{"parish":"Ceres","num_entries":"2","lat":"56.29243850708008","lon":"-2.9704926013946533"}],"1690":[],"1700":[],"1710":[{"parish":"Pittenweem","num_entries":"3","lat":"56.21339797973633","lon":"-2.7298381328582764"}],"1720":[],"1730":[],"1740":[{"parish":"Kingsbarns","num_entries":"3","lat":"56.29894256591797","lon":"-2.6601738929748535"}],"1750":[],"1760":[{"parish":"St Cuthbert's","num_entries":"1","lat":"55.946285247802734","lon":"-3.2164969444274902"}],"1770":[{"parish":"Crail","num_entries":"3","lat":"56.260677337646484","lon":"-2.626711845397949"}],"1780":[{"parish":"Dunbar","num_entries":"3","lat":"56.002140045166016","lon":"-2.5158236026763916"},{"parish":"Bothkennar","num_entries":"1","lat":"56.118125915527344","lon":"-3.9360013008117676"}],"1790":[{"parish":"Bothkennar","num_entries":"1","lat":"56.118125915527344","lon":"-3.9360013008117676"},{"parish":"Crail","num_entries":"1","lat":"56.260677337646484","lon":"-2.626711845397949"}],"1800":[{"parish":"Dunbar","num_entries":"2","lat":"56.002140045166016","lon":"-2.5158236026763916"},{"parish":"Crail","num_entries":"1","lat":"56.260677337646484","lon":"-2.626711845397949"},{"parish":"Anstruther Wester","num_entries":"1","lat":"56.220706939697266","lon":"-2.7077159881591797"}],"1810":[{"parish":"Pittenweem","num_entries":"4","lat":"56.21339797973633","lon":"-2.7298381328582764"},{"parish":"Leith South","num_entries":"4","lat":"55.946285247802734","lon":"-3.2164969444274902"},{"parish":"Ceres","num_entries":"2","lat":"56.29243850708008","lon":"-2.9704926013946533"},{"parish":"Kilninian and Kilmore","num_entries":"1","lat":"56.373443603515625","lon":"-5.437215805053711"},{"parish":"Cambusnethan","num_entries":"1","lat":"55.77961349487305","lon":"-3.8999598026275635"}],"1820":[{"parish":"Falkirk","num_entries":"4","lat":"56.06751251220703","lon":"-3.877908945083618"},{"parish":"Leith South","num_entries":"3","lat":"55.946285247802734","lon":"-3.2164969444274902"},{"parish":"Ceres","num_entries":"2","lat":"56.29243850708008","lon":"-2.9704926013946533"}],"1830":[{"parish":"Falkirk","num_entries":"2","lat":"56.06751251220703","lon":"-3.877908945083618"},{"parish":"Ceres","num_entries":"1","lat":"56.29243850708008","lon":"-2.9704926013946533"},{"parish":"Glasgow","num_entries":"1","lat":"55.855018615722656","lon":"-4.562086582183838"},{"parish":"Thurso","num_entries":"1","lat":"58.59474563598633","lon":"-3.5205769538879395"}],"1840":[{"parish":"Ceres","num_entries":"2","lat":"56.29243850708008","lon":"-2.9704926013946533"},{"parish":"Wick","num_entries":"1","lat":"58.44255065917969","lon":"-3.091582775115967"},{"parish":"Glasgow","num_entries":"1","lat":"55.855018615722656","lon":"-4.562086582183838"}],"1850":[{"parish":"Ceres","num_entries":"8","lat":"56.29243850708008","lon":"-2.9704926013946533"},{"parish":"Glasgow","num_entries":"3","lat":"55.855018615722656","lon":"-4.562086582183838"}],"1860":[{"parish":"Ceres","num_entries":"3","lat":"56.29243850708008","lon":"-2.9704926013946533"},{"parish":"High Church","num_entries":"1","lat":"55.853755950927734","lon":"-4.241918087005615"},{"parish":"Leith South","num_entries":"1","lat":"55.946285247802734","lon":"-3.2164969444274902"}],"1870":[{"parish":"St George","num_entries":"4","lat":"55.946285247802734","lon":"-3.2164969444274902"},{"parish":"Dunfermline Burgh","num_entries":"2","lat":"56.33333206176758","lon":"-3"},{"parish":"St Andrews and St Leonards","num_entries":"1","lat":"56.340389251708984","lon":"-2.7955844402313232"},{"parish":"Perth","num_entries":"1","lat":"56.391475677490234","lon":"-3.4383962154388428"},{"parish":"Dunfermline","num_entries":"1","lat":"56.071372985839844","lon":"-3.461618185043335"}],"1880":[{"parish":"Perth","num_entries":"4","lat":"56.391475677490234","lon":"-3.4383962154388428"},{"parish":"St Andrew","num_entries":"4","lat":"56.481956481933594","lon":"-3.0189971923828125"},{"parish":"Dennistoun","num_entries":"3","lat":"55.853755950927734","lon":"-4.241918087005615"},{"parish":"St Rollox","num_entries":"3","lat":"55.853755950927734","lon":"-4.241918087005615"},{"parish":"Newington","num_entries":"2","lat":"55.946285247802734","lon":"-3.2164969444274902"}],"1890":[{"parish":"St Andrew","num_entries":"4","lat":"56.481956481933594","lon":"-3.0189971923828125"},{"parish":"Perth","num_entries":"3","lat":"56.391475677490234","lon":"-3.4383962154388428"},{"parish":"Aberdeen Old Machar","num_entries":"2","lat":"57.14265060424805","lon":"-2.0976345539093018"},{"parish":"Milton","num_entries":"2","lat":"55.853755950927734","lon":"-4.241918087005615"},{"parish":"Dennistoun","num_entries":"2","lat":"55.853755950927734","lon":"-4.241918087005615"}]}},"deaths":{"totals":{"1770":"1","1790":"1","1810":"5","1820":"2","1830":"3","1840":"4","1850":"7","1860":"1","1870":"9","1880":"10","1890":"12","1560":0,"1570":0,"1580":0,"1590":0,"1600":0,"1610":0,"1620":0,"1630":0,"1640":0,"1650":0,"1660":0,"1670":0,"1680":0,"1690":0,"1700":0,"1710":0,"1720":0,"1730":0,"1740":0,"1750":0,"1760":0,"1780":0,"1800":0},"topParishes":{"1560":[],"1570":[],"1580":[],"1590":[],"1600":[],"1610":[],"1620":[],"1630":[],"1640":[],"1650":[],"1660":[],"1670":[],"1680":[],"1690":[],"1700":[],"1710":[],"1720":[],"1730":[],"1740":[],"1750":[],"1760":[],"1770":[{"parish":"Anstruther Easter","num_entries":"1","lat":"56.22429275512695","lon":"-2.6983389854431152"}],"1780":[],"1790":[{"parish":"Bothkennar","num_entries":"1","lat":"56.118125915527344","lon":"-3.9360013008117676"}],"1800":[],"1810":[{"parish":"Dunbar","num_entries":"2","lat":"56.002140045166016","lon":"-2.5158236026763916"},{"parish":"Pittenweem","num_entries":"2","lat":"56.21339797973633","lon":"-2.7298381328582764"},{"parish":"Tranent","num_entries":"1","lat":"55.944496154785156","lon":"-2.95349383354187"}],"1820":[{"parish":"Dunbar","num_entries":"1","lat":"56.002140045166016","lon":"-2.5158236026763916"},{"parish":"Pittenweem","num_entries":"1","lat":"56.21339797973633","lon":"-2.7298381328582764"}],"1830":[{"parish":"Canongate","num_entries":"2","lat":"55.946285247802734","lon":"-3.2164969444274902"},{"parish":"Ceres","num_entries":"1","lat":"56.29243850708008","lon":"-2.9704926013946533"}],"1840":[{"parish":"Melrose","num_entries":"1","lat":"55.56855392456055","lon":"-2.478135824203491"},{"parish":"Leith North","num_entries":"1","lat":"55.946285247802734","lon":"-3.2164969444274902"},{"parish":"St Andrews and St Leonards","num_entries":"1","lat":"56.340389251708984","lon":"-2.7955844402313232"},{"parish":"Ceres","num_entries":"1","lat":"56.29243850708008","lon":"-2.9704926013946533"}],"1850":[{"parish":"Ceres","num_entries":"2","lat":"56.29243850708008","lon":"-2.9704926013946533"},{"parish":"Carnbee","num_entries":"1","lat":"56.24957275390625","lon":"-2.7582192420959473"},{"parish":"Leith North","num_entries":"1","lat":"55.946285247802734","lon":"-3.2164969444274902"},{"parish":"Newington","num_entries":"1","lat":"55.946285247802734","lon":"-3.2164969444274902"},{"parish":"Glasgow Central District","num_entries":"1","lat":"55.853755950927734","lon":"-4.241918087005615"}],"1860":[{"parish":"Glasgow Central District","num_entries":"1","lat":"55.853755950927734","lon":"-4.241918087005615"}],"1870":[{"parish":"Ceres","num_entries":"3","lat":"56.29243850708008","lon":"-2.9704926013946533"},{"parish":"Dunbar","num_entries":"1","lat":"56.002140045166016","lon":"-2.5158236026763916"},{"parish":"Blythswood","num_entries":"1","lat":"55.853755950927734","lon":"-4.241918087005615"},{"parish":"Leith South","num_entries":"1","lat":"55.946285247802734","lon":"-3.2164969444274902"},{"parish":"St George","num_entries":"1","lat":"55.946285247802734","lon":"-3.2164969444274902"}],"1880":[{"parish":"Ceres","num_entries":"2","lat":"56.29243850708008","lon":"-2.9704926013946533"},{"parish":"St Rollox","num_entries":"2","lat":"55.853755950927734","lon":"-4.241918087005615"},{"parish":"Perth","num_entries":"2","lat":"56.391475677490234","lon":"-3.4383962154388428"},{"parish":"Wick","num_entries":"1","lat":"58.44255065917969","lon":"-3.091582775115967"},{"parish":"Leith South","num_entries":"1","lat":"55.946285247802734","lon":"-3.2164969444274902"}],"1890":[{"parish":"Ceres","num_entries":"2","lat":"56.29243850708008","lon":"-2.9704926013946533"},{"parish":"Coatbridge or Old Monkland","num_entries":"2","lat":"55.86228561401367","lon":"-4.027316570281982"},{"parish":"Dunfermline","num_entries":"2","lat":"56.071372985839844","lon":"-3.461618185043335"},{"parish":"Leith North","num_entries":"1","lat":"55.946285247802734","lon":"-3.2164969444274902"},{"parish":"Canongate","num_entries":"1","lat":"55.946285247802734","lon":"-3.2164969444274902"}]}},"marriages":{"totals":{"1670":"2","1700":"1","1730":"3","1760":"2","1770":"4","1780":"1","1800":"4","1810":"8","1820":"4","1830":"8","1840":"8","1850":"3","1870":"7","1880":"7","1890":"2","1560":0,"1570":0,"1580":0,"1590":0,"1600":0,"1610":0,"1620":0,"1630":0,"1640":0,"1650":0,"1660":0,"1680":0,"1690":0,"1710":0,"1720":0,"1740":0,"1750":0,"1790":0,"1860":0},"topParishes":{"1560":[],"1570":[],"1580":[],"1590":[],"1600":[],"1610":[],"1620":[],"1630":[],"1640":[],"1650":[],"1660":[],"1670":[{"parish":"St Andrews and St Leonards","num_entries":"2","lat":"56.340389251708984","lon":"-2.7955844402313232"}],"1680":[],"1690":[],"1700":[{"parish":"Ceres","num_entries":"1","lat":"56.29243850708008","lon":"-2.9704926013946533"}],"1710":[],"1720":[],"1730":[{"parish":"Kingsbarns","num_entries":"2","lat":"56.29894256591797","lon":"-2.6601738929748535"},{"parish":"Crail","num_entries":"1","lat":"56.260677337646484","lon":"-2.626711845397949"}],"1740":[],"1750":[],"1760":[{"parish":"Crail","num_entries":"2","lat":"56.260677337646484","lon":"-2.626711845397949"}],"1770":[{"parish":"Crail","num_entries":"3","lat":"56.260677337646484","lon":"-2.626711845397949"},{"parish":"Bothkennar","num_entries":"1","lat":"56.118125915527344","lon":"-3.9360013008117676"}],"1780":[{"parish":"Pittenweem","num_entries":"1","lat":"56.21339797973633","lon":"-2.7298381328582764"}],"1790":[],"1800":[{"parish":"Dunbar","num_entries":"2","lat":"56.002140045166016","lon":"-2.5158236026763916"},{"parish":"Inveresk and Musselburgh","num_entries":"1","lat":"55.89702224731445","lon":"-3.0553297996520996"},{"parish":"Edinburgh","num_entries":"1","lat":"55.899864196777344","lon":"-3.0929973125457764"}],"1810":[{"parish":"Leith South","num_entries":"3","lat":"55.946285247802734","lon":"-3.2164969444274902"},{"parish":"Kingsbarns","num_entries":"1","lat":"56.29894256591797","lon":"-2.6601738929748535"},{"parish":"Glasgow","num_entries":"1","lat":"55.855018615722656","lon":"-4.562086582183838"},{"parish":"Canongate","num_entries":"1","lat":"55.946285247802734","lon":"-3.2164969444274902"},{"parish":"Leuchars","num_entries":"1","lat":"56.37479782104492","lon":"-2.8938546180725098"}],"1820":[{"parish":"Kilconquhar","num_entries":"1","lat":"56.209712982177734","lon":"-2.82861590385437"},{"parish":"Glasgow","num_entries":"1","lat":"55.855018615722656","lon":"-4.562086582183838"},{"parish":"Leith South","num_entries":"1","lat":"55.946285247802734","lon":"-3.2164969444274902"},{"parish":"Crail","num_entries":"1","lat":"56.260677337646484","lon":"-2.626711845397949"}],"1830":[{"parish":"Dunbar","num_entries":"1","lat":"56.002140045166016","lon":"-2.5158236026763916"},{"parish":"Glasgow","num_entries":"1","lat":"55.855018615722656","lon":"-4.562086582183838"},{"parish":"St Cuthbert's","num_entries":"1","lat":"55.946285247802734","lon":"-3.2164969444274902"},{"parish":"Reay","num_entries":"1","lat":"58.55859375","lon":"-3.7759721279144287"},{"parish":"Ceres","num_entries":"1","lat":"56.29243850708008","lon":"-2.9704926013946533"}],"1840":[{"parish":"Wick","num_entries":"2","lat":"58.44255065917969","lon":"-3.091582775115967"},{"parish":"Ceres","num_entries":"2","lat":"56.29243850708008","lon":"-2.9704926013946533"},{"parish":"Old Monkland or Coatbridge","num_entries":"1","lat":"55.847076416015625","lon":"-4.048725128173828"},{"parish":"Kinghorn","num_entries":"1","lat":"56.070735931396484","lon":"-3.1742284297943115"},{"parish":"Kingsbarns","num_entries":"1","lat":"56.29894256591797","lon":"-2.6601738929748535"}],"1850":[{"parish":"Ceres","num_entries":"1","lat":"56.29243850708008","lon":"-2.9704926013946533"},{"parish":"Glasgow","num_entries":"1","lat":"55.855018615722656","lon":"-4.562086582183838"},{"parish":"Dunkeld","num_entries":"1","lat":"56.56557083129883","lon":"-3.586254596710205"}],"1860":[],"1870":[{"parish":"Perth","num_entries":"2","lat":"56.391475677490234","lon":"-3.4383962154388428"},{"parish":"Canongate","num_entries":"1","lat":"55.946285247802734","lon":"-3.2164969444274902"},{"parish":"St George","num_entries":"1","lat":"55.946285247802734","lon":"-3.2164969444274902"},{"parish":"Leith North","num_entries":"1","lat":"55.946285247802734","lon":"-3.2164969444274902"},{"parish":"Lochee","num_entries":"1","lat":"56.4727783203125","lon":"-3.0121123790740967"}],"1880":[{"parish":"Kelvin","num_entries":"2","lat":"55.93818664550781","lon":"-4.191908359527588"},{"parish":"Leith North","num_entries":"1","lat":"55.946285247802734","lon":"-3.2164969444274902"},{"parish":"St Giles","num_entries":"1","lat":"55.946285247802734","lon":"-3.2164969444274902"},{"parish":"Blythswood","num_entries":"1","lat":"55.853755950927734","lon":"-4.241918087005615"},{"parish":"Glenshee","num_entries":"1","lat":"56.741031646728516","lon":"-3.399935245513916"}],"1890":[{"parish":"Stirling","num_entries":"1","lat":"56.118125915527344","lon":"-3.9360013008117676"},{"parish":"Kelvin","num_entries":"1","lat":"55.93818664550781","lon":"-4.191908359527588"}]}}}